MANIFEST.in
Makefile
README.md
ovirt-imageio
ovirt-imageio.spec.in
ovirt-imageioctl
ovirt-img
setup.py
storage.py
tox.ini
LICENSES/GPL-2.0-or-later.txt
build-aux/release
container/app/entrypoint.py
data/README
data/ovirt-imageio.service
docs/_config.yml
docs/configuration.md
docs/container.md
docs/development.md
docs/flows.md
docs/images.md
docs/index.md
docs/installation.md
docs/overview.md
docs/packages.md
docs/unix-socket.md
examples/checksum
examples/file.json
examples/file.json.license
examples/imageio-client
examples/libvirt-stream
examples/nbd.json
examples/nbd.json.license
examples/sparse-stream
examples/conf.d/daemon.conf
ovirt_imageio/__init__.py
ovirt_imageio.egg-info/PKG-INFO
ovirt_imageio.egg-info/SOURCES.txt
ovirt_imageio.egg-info/dependency_links.txt
ovirt_imageio.egg-info/top_level.txt
ovirt_imageio/_internal/__init__.py
ovirt_imageio/_internal/auth.py
ovirt_imageio/_internal/blkhash.py
ovirt_imageio/_internal/config.py
ovirt_imageio/_internal/configloader.py
ovirt_imageio/_internal/cors.py
ovirt_imageio/_internal/directio.py
ovirt_imageio/_internal/errors.py
ovirt_imageio/_internal/extent.py
ovirt_imageio/_internal/http.py
ovirt_imageio/_internal/ioutil.c
ovirt_imageio/_internal/ipv6.py
ovirt_imageio/_internal/measure.py
ovirt_imageio/_internal/nbd.py
ovirt_imageio/_internal/nbdutil.py
ovirt_imageio/_internal/ops.py
ovirt_imageio/_internal/qemu_img.py
ovirt_imageio/_internal/qemu_nbd.py
ovirt_imageio/_internal/server.py
ovirt_imageio/_internal/services.py
ovirt_imageio/_internal/sockutil.py
ovirt_imageio/_internal/ssl.py
ovirt_imageio/_internal/stats.py
ovirt_imageio/_internal/uhttp.py
ovirt_imageio/_internal/units.py
ovirt_imageio/_internal/util.py
ovirt_imageio/_internal/validate.py
ovirt_imageio/_internal/version.py
ovirt_imageio/_internal/backends/__init__.py
ovirt_imageio/_internal/backends/common.py
ovirt_imageio/_internal/backends/file.py
ovirt_imageio/_internal/backends/http.py
ovirt_imageio/_internal/backends/memory.py
ovirt_imageio/_internal/backends/nbd.py
ovirt_imageio/_internal/handlers/checksum.py
ovirt_imageio/_internal/handlers/extents.py
