Metadata-Version: 2.4
Name: ovirt-imageio
Version: 2.5.1
Summary: Transfer disk images on oVirt system
Home-page: https://github.com/oVirt/ovirt-imageio
Author: oVirt Authors
Author-email: devel@ovirt.org
License: GNU GPLv2+
Project-URL: Documentation, http://ovirt.github.io/ovirt-imageio/
Project-URL: Bug Tracker, https://github.com/oVirt/ovirt-imageio/issues
Platform: Linux
Classifier: Development Status :: 5 - Production/Stable
Classifier: Intended Audience :: Developers
Classifier: Intended Audience :: System Administrators
Classifier: Programming Language :: Python :: 3.6
Classifier: Programming Language :: Python :: 3.7
Classifier: Programming Language :: Python :: 3.8
Classifier: Programming Language :: Python :: 3.9
Classifier: Programming Language :: Python :: 3.10
Classifier: Programming Language :: Python :: 3.11
Classifier: Topic :: System :: Archiving :: Backup
Classifier: Topic :: Utilities
Requires-Python: >=3.6
Dynamic: author
Dynamic: author-email
Dynamic: classifier
Dynamic: description
Dynamic: description-content-type
Dynamic: home-page
Dynamic: license
Dynamic: platform
Dynamic: project-url
Dynamic: requires-python
Dynamic: summary
